AgoraQuant/CreditRisk.py
AgoraQuant/__init__.py
AgoraQuant/example.py
agoraquant-0.0.1.dist-info/METADATA
agoraquant-0.0.1.dist-info/WHEEL
agoraquant-0.0.1.dist-info/licenses/LICENSE.txt
agoraquant-0.0.1.dist-info/RECORD
