Metadata-Version: 2.1
Name: AgoraQuant
Version: 0.0.1
Summary: Provides more complete output for quantitative model development.
Project-URL: Homepage, https://github.com/dimitribianco/AgoraQuant.git
Project-URL: Bug Tracker, https://github.com/dimitribianco/AgoraQuant/issues
Author-email: Dimitri Bianco <dimitri.bianco@agoradata.com>
License-File: LICENSE.txt
Classifier: License :: OSI Approved :: MIT License
Classifier: Operating System :: OS Independent
Classifier: Programming Language :: Python :: 3
Requires-Python: >=3.7
